WFM4Cities/Water_flooding_Model.py
WFM4Cities/__init__.py
WFM4Cities-2.6.dist-info/METADATA
WFM4Cities-2.6.dist-info/WHEEL
WFM4Cities-2.6.dist-info/entry_points.txt
WFM4Cities-2.6.dist-info/top_level.txt
WFM4Cities-2.6.dist-info/RECORD
