Metadata-Version: 2.1
Name: WFM4Cities
Version: 2.6
Summary: Water-flooding Method for urban 3D-morphology
Home-page: https://github.com/你的用户名/你的项目
Author: 张祚, 江驭鲲, 王哲
Author-email: jiangyukunccnu@163.com
Classifier: Programming Language :: Python :: 3
Classifier: License :: OSI Approved :: MIT License
Classifier: Operating System :: OS Independent
Classifier: Intended Audience :: Science/Research
Classifier: Natural Language :: English
Requires-Python: >=3.6
Requires-Dist: scipy==1.13.1
Requires-Dist: scikit-learn==1.3.0
Requires-Dist: matplotlib==3.9.4
Requires-Dist: geopandas==0.13.1
Requires-Dist: shapely==2.0.6
Requires-Dist: pysal==24.1
Requires-Dist: numpy==1.25.2
